fplanck/__init__.py
fplanck/cli.py
fplanck/examples/free_space.py
fplanck/examples/harmonic.py
fplanck/examples/harmonic_2d.py
fplanck/examples/nonuniform_diffusion.py
fplanck/examples/periodic.py
fplanck/examples/ratchet.py
fplanck/examples/ring.py
fplanck/examples/tilted_bigaussian.py
fplanck/forces.py
fplanck/functions.py
fplanck/potentials.py
fplanck/py.typed
fplanck/solver.py
fplanck/utility.py
fplanck-1.0.2.dist-info/WHEEL
fplanck-1.0.2.dist-info/entry_points.txt
fplanck-1.0.2.dist-info/METADATA
fplanck-1.0.2.dist-info/RECORD
