Metadata-Version: 2.3
Name: fplanck
Version: 1.0.2
Summary: Solve the Fokker-Planck equation in N dimensions
Author: John Parker
Author-email: John Parker <johnaparker@users.noreply.github.com>
Requires-Dist: matplotlib>=3.10.7
Requires-Dist: numpy>=2.3.3
Requires-Dist: pandas>=2.3.3
Requires-Dist: scipy>=1.16.2
Requires-Python: >=3.12.0
